pcpartpicker_flask/__init__.py
pcpartpicker_flask/api.py
pcpartpicker_flask/errors.py
pcpartpicker_flask/handler.py
pcpartpicker_flask/mappings.py
pcpartpicker_flask/parse_utils.py
pcpartpicker_flask/part_data.py
pcpartpicker_flask/parts.py
pcpartpicker_flask/scraper.py
pcpartpicker_flask/utils.py
pcpartpicker_flask-3.1.1.dist-info/LICENSE
pcpartpicker_flask-3.1.1.dist-info/METADATA
pcpartpicker_flask-3.1.1.dist-info/WHEEL
pcpartpicker_flask-3.1.1.dist-info/top_level.txt
pcpartpicker_flask-3.1.1.dist-info/RECORD
