Metadata-Version: 2.1
Name: pcpartpicker-flask
Version: 3.1.1
Summary: A fast, simple API for PCPartPicker.com.
Home-page: https://github.com/carlbeattie2000/pcpartpicker-flask
Author: Jonathan Vusich
Author-email: jonathanvusich@gmail.com
License: GPL
Keywords: pcpartpicker api webscraper python3
Platform: UNKNOWN
Classifier: Development Status :: 5 - Production/Stable
Classifier: Topic :: Utilities
Classifier: License :: OSI Approved :: GNU General Public License v3 (GPLv3)
License-File: LICENSE
Requires-Dist: py-moneyed (==0.8.0)
Requires-Dist: dacite (==1.6.0)
Requires-Dist: aiohttp (==3.7.4)
